remotecheck/__init__.py
remotecheck/check.py
remotecheck/checkargs.py
remotecheck/exceptions.py
remotecheck/sensor.py
remotecheck/settings.py
remotecheck/tcpport.py
remotecheck/unused_forcedip.py
remotecheck/version.py
okerrsensor-0.0.73.dist-info/METADATA
okerrsensor-0.0.73.dist-info/WHEEL
okerrsensor-0.0.73.dist-info/entry_points.txt
okerrsensor-0.0.73.dist-info/licenses/LICENSE
okerrsensor-0.0.73.dist-info/RECORD
