Metadata-Version: 2.4
Name: okerrsensor
Version: 0.0.73
Summary: network sensor for okerr monitoring server
Project-URL: homepage, https://gitlab.com/yaroslaff/sensor
Author-email: Yaroslav Polyakov <yaroslaff@gmail.com>
License: MIT License
License-File: LICENSE
Classifier: Development Status :: 3 - Alpha
Classifier: Intended Audience :: Developers
Classifier: License :: OSI Approved :: GNU General Public License (GPL)
Requires-Python: >=3
Requires-Dist: async-dnsbl-client>=0.0.3
Requires-Dist: dnspython
Requires-Dist: forcediphttpsadapter
Requires-Dist: icmplib
Requires-Dist: okerrupdate
Requires-Dist: pika
Requires-Dist: pika>=1.1.0
Requires-Dist: pyopenssl
Requires-Dist: python-dotenv
Requires-Dist: python-whois
Requires-Dist: setproctitle
